Workbook

Sheet Config
A1: Payment Basis | B1: 17954250
A2: GST Rate | B2: 0.05
A3: TDS Rate | B3: 0.01
A4: Stamp Duty Rate | B4: 0.06

Sheet Cost Sheet & Payment Schedule
A1: Project Name: "TRIRATNA"
A2: Plot No. 164, RDP-7, Part-II, Sector-3, Charkop, Kandivali (West), Mumbai - 400067
F3: Expression of Interest in Proposed Self-Redevelopment
A4: 1 | B4: Available Flat | C4: 2102 | F4: Payment Schedule For : 2102
A5: 2 | B5: Configuration | C5: FP-7 | F5: Milestone | G5: Net | H5: Tentative | I5: Cuml. | J5: Amount | K5: TDS | L5: GST 5%
C6: Unit | D6: Amount | F6: EOI | G6: 0.1 | H6: Due | I6: =SUM($G$6:G6) -> 0.1 | J6: =Config!B1*G6 -> 1795425 | K6: =J6*Config!B3 -> 17954.25 | L6: =J6*Config!B2 -> 89771.25
A7: A | B7: Flat Area | C7: SFt. | D7: 718.17 | F7: On Registration of Sales Agreement | G7: 0.2 | I7: =SUM($G$6:G7) -> 0.3 | J7: =Config!B1*G7 -> 3590850 | K7: =J7*Config!B3 -> 35908.5 | L7: =J7*Config!B2 -> 179542.5
A8: B | B8: Flat Rate | C8: /SFt. | D8: 25000 | F8: On Completion of Plinth | G8: 0.15 | I8: =SUM($G$6:G8) -> 0.45 | J8: =Config!B1*G8 -> 2693137.5 | K8: =J8*Config!B3 -> 26931.38 | L8: =J8*Config!B2 -> 134656.88
F9: On Slab wise upto 14th Floor (due as per slab)*** | G9: 0.25 | I9: =SUM($G$6:G9) -> 0.7 | J9: =Config!B1*G9 -> 4488562.5 | K9: =J9*Config!B3 -> 44885.63 | L9: =J9*Config!B2 -> 224428.13
A10: C | B10: Flat Cost | C10: Rs. | D10: =D7*D8 -> 17954250 | F10: On Execution of Internal Amenities of Flat | G10: 0.1 | I10: =SUM($G$6:G10) -> 0.8 | J10: =Config!B1*G10 -> 1795425 | K10: =J10*Config!B3 -> 17954.25 | L10: =J10*Config!B2 -> 89771.25
F11: On Execution of External Amenities of Flat | G11: 0.1 | I11: =SUM($G$6:G11) -> 0.9 | J11: =Config!B1*G11 -> 1795425 | K11: =J11*Config!B3 -> 17954.25 | L11: =J11*Config!B2 -> 89771.25
A12: D | B12: No. of Parking | C12: No | D12: 0 | F12: On Execution of Lift & Paint | G12: 0.05 | I12: =SUM($G$6:G12) -> 0.95 | J12: =Config!B1*G12 -> 897712.5 | K12: =J12*Config!B3 -> 8977.13 | L12: =J12*Config!B2 -> 44885.63
B13: Parking Cost | C13: Rs. | D13: 0 | F13: Before handing over or on receipt of OC | G13: 0.05 | I13: =SUM($G$6:G13) -> 1 | J13: =Config!B1*G13 -> 897712.5 | K13: =J13*Config!B3 -> 8977.13 | L13: =J13*Config!B2 -> 44885.63
A15: E | B15: Total Flat Cost | C15: Rs. | D15: =D10+D13 -> 17954250
A17: Other Cost
A18: 1 | B18: GST @ 5% | C18: Rs. | D18: =D15*Config!B2 -> 897712.5
A19: 2 | B19: Stamp Duty 6% | C19: Rs. | D19: =D15*Config!B4 -> 1077255
A20: 3 | B20: Registration Charges | C20: Rs. | D20: 3000
A21: F | B21: Sub Total | C21: Rs. | D21: =SUM(D18:D20) -> 1977967.5
A23: G | B23: TOTAL ( E + F ) | C23: Rs. | D23: =D15+D21 -> 19932218 | F23: Total | I23: =SUM(G6:G13) -> 1 | J23: =SUM(J6:J13) -> 17954250 | K23: =SUM(K6:K13) -> 179542.52 | L23: =SUM(L6:L13) -> 897712.52
F24: GST & Stamp Duty is as per the prevailing Govt. Norms. Society Development charges shall be applicable at the time of possessions as decided by society proportionate to all.
B25: For TRIRATNA
B29: Authorised Signatory
A31: I/We hear by accept and confirm the terms
A32: Name | B32: mcube k
A33: Sign | C33: Date | D33: 22/9/2026
A35: NOTE: Committee Reserve the rights to change the price, configuration if not booked (rates are for 7 days).
